geodynamic/__init__.py
geodynamic/__main__.py
geodynamic/manim_dynamic.py
geodynamic/geo/__init__.py
geodynamic/geo/construction.py
geodynamic/geo/lib_commands.py
geodynamic/geo/lib_elements.py
geodynamic/geo/lib_vars.py
geodynamic/parsers/__init__.py
geodynamic/parsers/ggb_generator.py
geodynamic/parsers/ggb_parser.py
geodynamic/parsers/short_parser.py
geodynamic/parsers/svg_parser.py
geodynamic-0.0.31.dist-info/licenses/LICENSE.txt
geodynamic-0.0.31.dist-info/METADATA
geodynamic-0.0.31.dist-info/WHEEL
geodynamic-0.0.31.dist-info/entry_points.txt
geodynamic-0.0.31.dist-info/top_level.txt
geodynamic-0.0.31.dist-info/RECORD
