Metadata-Version: 2.4
Name: geodynamic
Version: 0.0.31
Summary: Geometric tools for parsing GeoGebra construction, proccess with manim animation and export to SVG
Home-page: https://pypi.org/project/geodynamic/
Author: ivaleo
Author-email: ivaleotion@gmail.com
Keywords: geometry dynamic geogebra manim animation svg python
Classifier: Programming Language :: Python :: 3.11
Classifier: License :: OSI Approved :: MIT License
Classifier: Operating System :: OS Independent
Requires-Python: >=3.11
License-File: LICENSE.txt
Requires-Dist: requests>=2.25.1
Requires-Dist: numpy>=1.26.0
Requires-Dist: manim>=0.19.0
Requires-Dist: pycairo>=1.0.0
Dynamic: author
Dynamic: author-email
Dynamic: classifier
Dynamic: description
Dynamic: description-content-type
Dynamic: home-page
Dynamic: keywords
Dynamic: license-file
Dynamic: requires-dist
Dynamic: requires-python
Dynamic: summary
